setup.py
src/qmarkdown/__init__.py
src/qmarkdown/qmarkdown.py
src/qmarkdown.egg-info/PKG-INFO
src/qmarkdown.egg-info/SOURCES.txt
src/qmarkdown.egg-info/dependency_links.txt
src/qmarkdown.egg-info/requires.txt
src/qmarkdown.egg-info/top_level.txt