Metadata-Version: 1.0
Name: qmarkdown
Version: 0.0.2
Summary: self module for writing markdown in python.
Home-page: UNKNOWN
Author: zwy
Author-email: zuowangyang@foxmail.com
License: MIT License
Keywords: markdown
Platform: any
